waldur_jira/__init__.py
waldur_jira/admin.py
waldur_jira/apps.py
waldur_jira/backend.py
waldur_jira/executors.py
waldur_jira/extension.py
waldur_jira/filters.py
waldur_jira/handlers.py
waldur_jira/log.py
waldur_jira/models.py
waldur_jira/serializers.py
waldur_jira/urls.py
waldur_jira/views.py
waldur_jira/migrations/0001_initial.py
waldur_jira/migrations/__init__.py
waldur_jira-0.4.0.dist-info/DESCRIPTION.rst
waldur_jira-0.4.0.dist-info/METADATA
waldur_jira-0.4.0.dist-info/RECORD
waldur_jira-0.4.0.dist-info/WHEEL
waldur_jira-0.4.0.dist-info/entry_points.txt
waldur_jira-0.4.0.dist-info/metadata.json
waldur_jira-0.4.0.dist-info/top_level.txt
